README.md
setup.py
pypi_scraper/__init__.py
pypi_scraper.egg-info/PKG-INFO
pypi_scraper.egg-info/SOURCES.txt
pypi_scraper.egg-info/dependency_links.txt
pypi_scraper.egg-info/requires.txt
pypi_scraper.egg-info/top_level.txt